{
    "preference_matrix": {
        "CruzOpenFeatureRequests, ProductEvolution": "1/8",
        "CruzOpenFeatureRequests, Support Community": "1/9",
        "CruzOpenFeatureRequests, Short-term Support": "1/7",
        "CruzOpenFeatureRequests, Community Exists": "1/8",
        "CruzOpenFeatureRequests, Contact within reasonable time": "1/6",
        "CruzOpenFeatureRequests, Complexity - by Mijinyawa et al.": "1/4",
        "CruzOpenFeatureRequests, Community Vitality": "1/7",
        "ProductEvolution, Support Community": "1",
        "ProductEvolution, Short-term Support": "1",
        "ProductEvolution, Community Exists": "1",
        "ProductEvolution, Contact within reasonable time": "2",
        "ProductEvolution, Complexity - by Mijinyawa et al.": "2",
        "ProductEvolution, Community Vitality": "1",
        "Support Community, Short-term Support": "1",
        "Support Community, Community Exists": "3",
        "Support Community, Contact within reasonable time": "2",
        "Support Community, Complexity - by Mijinyawa et al.": "3",
        "Support Community, Community Vitality": "1",
        "Short-term Support, Community Exists": "2",
        "Short-term Support, Contact within reasonable time": "2",
        "Short-term Support, Complexity - by Mijinyawa et al.": "2",
        "Short-term Support, Community Vitality": "1",
        "Community Exists, Contact within reasonable time": "2",
        "Community Exists, Complexity - by Mijinyawa et al.": "2",
        "Community Exists, Community Vitality": "1",
        "Contact within reasonable time, Complexity - by Mijinyawa et al.": "3",
        "Contact within reasonable time, Community Vitality": "1/2",
        "Complexity - by Mijinyawa et al., Community Vitality": "1/4",
        "CruzOpenFeatureRequests, Complexity": "1/2",
        "CruzOpenFeatureRequests, Maintainer Organization": "1/5",
        "ProductEvolution, Complexity": "3",
        "ProductEvolution, Maintainer Organization": "3",
        "Support Community, Complexity": "4",
        "Support Community, Maintainer Organization": "4",
        "Short-term Support, Complexity": "5",
        "Short-term Support, Maintainer Organization": "1",
        "Community Exists, Complexity": "2",
        "Community Exists, Maintainer Organization": "2",
        "Contact within reasonable time, Complexity": "5",
        "Contact within reasonable time, Maintainer Organization": "1/2",
        "Complexity, Community Vitality": "1/4",
        "Complexity, Maintainer Organization": "1/4",
        "Community Vitality, Maintainer Organization": "3"
    }
}